README.rst
setup.py
parse_requirements_not_suckily/__init__.py
parse_requirements_not_suckily/parse.py
parse_requirements_not_suckily.egg-info/PKG-INFO
parse_requirements_not_suckily.egg-info/SOURCES.txt
parse_requirements_not_suckily.egg-info/dependency_links.txt
parse_requirements_not_suckily.egg-info/top_level.txt
parse_requirements_not_suckily.egg-info/zip-safe