Metadata-Version: 1.1
Name: parse-requirements-not-suckily
Version: 0.0.1
Summary: Wrapper for parse_requirements to make less painful
Home-page: https://github.com/narfman0/parse-requirements-not-suckily
Author: Jon Robison
Author-email: narfman0@gmail.com
License: LICENSE
Keywords: setup.py lazymode parse_requirements
Platform: UNKNOWN
Classifier: Development Status :: 4 - Beta
Classifier: License :: OSI Approved :: GNU General Public License v3 (GPLv3)
Classifier: Operating System :: OS Independent
Classifier: Programming Language :: Python
Classifier: Topic :: Software Development :: Libraries :: Python Modules
